prox_checker/__init__.py
prox_checker/core.py
prox_checker-0.1.0.dist-info/LICENSE
prox_checker-0.1.0.dist-info/METADATA
prox_checker-0.1.0.dist-info/WHEEL
prox_checker-0.1.0.dist-info/RECORD
